{
  "version": "v3.1",
  "timestamp_iso": "2025-08-14T21:41:49Z",
  "timestamp_compact": "20250814_214149",
  "total_symbols": 20,
  "payloads": [
    {
      "symbol": "AVAX/USD",
      "symbol_type": "crypto",
      "market_hours_state": "24x7",
      "divergence": -0.951,
      "confidence": 0.855,
      "volume_z": 0.337,
      "price_move_pct": 0.01,
      "action": "HOLD",
      "summary": "Analysis for AVAX/USD",
      "detail": "Basic analysis completed for AVAX/USD",
      "timestamp": "2025-08-15T03:11:49.290033",
      "source_diversity": {
        "unique": 3,
        "top_source_share": 0.54,
        "counts": {
          "source1": 2
        },
        "adjustment": -0.019
      },
      "cascade_detector": {
        "repetition_ratio": 0.53,
        "price_move_pct": 0.012116642882149739,
        "max_volume_z": 0.3372037398557044,
        "tag": "",
        "confidence_delta": 0.0
      },
      "contrarian_viewport": "",
      "timescale_scores": {
        "short": {
          "divergence": -0.761,
          "price_move_pct": 0.0036349928646449217,
          "volume_z": 0.3372037398557044
        },
        "mid": {
          "divergence": -1.046,
          "price_move_pct": 0.0072699857292898434,
          "volume_z": 0.26976299188456354
        },
        "long": {
          "divergence": -0.856,
          "price_move_pct": 0.012116642882149739,
          "volume_z": 0.20232224391342263
        },
        "combined_divergence": -0.951,
        "aligned_horizons": 1,
        "alignment_flag": false,
        "weights": {
          "short": 0.5,
          "mid": 0.35,
          "long": 0.15
        }
      },
      "confirmation_checks": [
        {
          "name": "price_vs_narrative",
          "passed": false,
          "delta": -0.02
        },
        {
          "name": "volume_support",
          "passed": true,
          "delta": 0.0
        },
        {
          "name": "timescale_alignment",
          "passed": false,
          "delta": 0.0
        }
      ],
      "confirmation_penalty": -0.02,
      "position_sizing": {
        "confidence": 0.8546325243476637,
        "target_R": 0.41,
        "notes": [
          "linear scaling"
        ],
        "params": {
          "conf_floor": 0.65,
          "conf_cap": 0.85,
          "min_R": 0.25,
          "max_R": 1.0,
          "used_vol_norm": null
        }
      },
      "evidence_line": null,
      "thesis": {
        "action": "Sell",
        "risk_band": "Medium",
        "readiness": "Now"
      },
      "plan": {
        "1h": {
          "entries": [
            {
              "type": "fade",
              "zone_or_trigger": [
                23.387373880000002,
                23.475404289999997
              ]
            }
          ],
          "invalidation": {
            "price": 23.50474776,
            "condition": "close above"
          },
          "targets": [
            {
              "label": "TP1",
              "price": 23.06459571
            },
            {
              "label": "TP2",
              "price": 22.829847949999998
            }
          ],
          "explain": "Bias down on 1h; using fade entries into structure (structure context). Strength elevated, timing now, action sell.",
          "source": "analysis"
        },
        "4h": {
          "entries": [
            {
              "type": "fade",
              "zone_or_trigger": [
                23.479429999999997,
                23.619049999999998
              ]
            }
          ],
          "invalidation": {
            "price": 23.793574999999997,
            "condition": "close above"
          },
          "targets": [
            {
              "label": "TP1",
              "price": 22.85114
            },
            {
              "label": "TP2",
              "price": 22.397375
            }
          ],
          "explain": "Bias down on 4h; using fade entries into structure (structure context). Strength elevated, timing now, action sell.",
          "source": "analysis"
        },
        "1D": {
          "entries": [
            {
              "type": "fade",
              "zone_or_trigger": [
                23.619049999999998,
                23.793574999999997
              ]
            }
          ],
          "invalidation": {
            "price": 23.9681,
            "condition": "close above"
          },
          "targets": [
            {
              "label": "TP1",
              "price": 22.5719
            },
            {
              "label": "TP2",
              "price": 21.8738
            }
          ],
          "explain": "Bias down on 1D; using fade entries into structure (structure context). Strength elevated, timing now, action sell.",
          "source": "analysis"
        },
        "1W": {
          "entries": [
            {
              "type": "fade",
              "zone_or_trigger": [
                23.9010824,
                24.216623600000002
              ]
            }
          ],
          "invalidation": {
            "price": 24.3743942,
            "condition": "close above"
          },
          "targets": [
            {
              "label": "TP1",
              "price": 22.007835200000002
            },
            {
              "label": "TP2",
              "price": 20.745670399999998
            }
          ],
          "explain": "Bias down on 1W; using fade entries into structure (structure context). Strength elevated, timing now, action sell.",
          "source": "analysis"
        }
      }
    },
    {
      "symbol": "BNB/USD",
      "symbol_type": "crypto",
      "market_hours_state": "24x7",
      "divergence": -0.845,
      "confidence": 0.656,
      "volume_z": 0.0,
      "price_move_pct": -0.17,
      "action": "HOLD",
      "summary": "Analysis for BNB/USD",
      "detail": "Basic analysis completed for BNB/USD",
      "timestamp": "2025-08-15T03:11:49.291145",
      "source_diversity": {
        "unique": 1,
        "top_source_share": 0.6,
        "counts": {
          "source1": 3
        },
        "adjustment": 0.028
      },
      "cascade_detector": {
        "repetition_ratio": 0.64,
        "price_move_pct": 0.16512394364306623,
        "max_volume_z": 0.00014854862350044407,
        "tag": "",
        "confidence_delta": 0.0
      },
      "contrarian_viewport": "",
      "timescale_scores": {
        "short": {
          "divergence": -0.676,
          "price_move_pct": 0.04953718309291987,
          "volume_z": 0.00014854862350044407
        },
        "mid": {
          "divergence": -0.929,
          "price_move_pct": 0.09907436618583974,
          "volume_z": 0.00011883889880035526
        },
        "long": {
          "divergence": -0.76,
          "price_move_pct": 0.16512394364306623,
          "volume_z": 8.912917410026644e-05
        },
        "combined_divergence": -0.845,
        "aligned_horizons": 1,
        "alignment_flag": false,
        "weights": {
          "short": 0.5,
          "mid": 0.35,
          "long": 0.15
        }
      },
      "confirmation_checks": [
        {
          "name": "price_vs_narrative",
          "passed": true,
          "delta": 0.0
        },
        {
          "name": "volume_support",
          "passed": true,
          "delta": 0.0
        },
        {
          "name": "timescale_alignment",
          "passed": false,
          "delta": 0.0
        }
      ],
      "confirmation_penalty": 0.0,
      "position_sizing": {
        "confidence": 0.6561342749444843,
        "target_R": 0.66,
        "notes": [
          "linear scaling"
        ],
        "params": {
          "conf_floor": 0.65,
          "conf_cap": 0.85,
          "min_R": 0.25,
          "max_R": 1.0,
          "used_vol_norm": null
        }
      },
      "evidence_line": null,
      "thesis": {
        "action": "Watch",
        "risk_band": "High",
        "readiness": "Near"
      },
      "plan": {
        "1h": {
          "entries": [
            {
              "type": "fade",
              "zone_or_trigger": [
                829.00136448,
                831.9123878400001
              ]
            }
          ],
          "invalidation": {
            "price": 832.8827289600001,
            "condition": "close above"
          },
          "targets": [
            {
              "label": "TP1",
              "price": 818.32761216
            },
            {
              "label": "TP2",
              "price": 810.5648832
            }
          ],
          "explain": "Bias down on 1h; using fade entries into structure (structure context). Strength elevated, timing near, action watch.",
          "source": "analysis"
        },
        "4h": {
          "entries": [
            {
              "type": "fade",
              "zone_or_trigger": [
                832.1945788800001,
                836.9109648
              ]
            }
          ],
          "invalidation": {
            "price": 842.8064472000001,
            "condition": "close above"
          },
          "targets": [
            {
              "label": "TP1",
              "price": 810.9708422399999
            },
            {
              "label": "TP2",
              "price": 795.642588
            }
          ],
          "explain": "Bias down on 4h; using fade entries into structure (structure context). Strength elevated, timing near, action watch.",
          "source": "analysis"
        },
        "1D": {
          "entries": [
            {
              "type": "fade",
              "zone_or_trigger": [
                836.9109648,
                842.8064472000001
              ]
            }
          ],
          "invalidation": {
            "price": 848.7019296000001,
            "condition": "close above"
          },
          "targets": [
            {
              "label": "TP1",
              "price": 801.5380703999999
            },
            {
              "label": "TP2",
              "price": 777.9561408
            }
          ],
          "explain": "Bias down on 1D; using fade entries into structure (structure context). Strength elevated, timing near, action watch.",
          "source": "analysis"
        },
        "1W": {
          "entries": [
            {
              "type": "fade",
              "zone_or_trigger": [
                845.913024,
                856.3095360000001
              ]
            }
          ],
          "invalidation": {
            "price": 861.507792,
            "condition": "close above"
          },
          "targets": [
            {
              "label": "TP1",
              "price": 783.533952
            },
            {
              "label": "TP2",
              "price": 741.947904
            }
          ],
          "explain": "Bias down on 1W; using fade entries into structure (structure context). Strength elevated, timing near, action watch.",
          "source": "analysis"
        }
      }
    },
    {
      "symbol": "BTC/USD",
      "symbol_type": "crypto",
      "market_hours_state": "24x7",
      "divergence": 0.823,
      "confidence": 0.786,
      "volume_z": 0.468,
      "price_move_pct": 0.86,
      "action": "HOLD",
      "summary": "Analysis for BTC/USD",
      "detail": "Basic analysis completed for BTC/USD",
      "timestamp": "2025-08-15T03:11:49.284501",
      "source_diversity": {
        "unique": 1,
        "top_source_share": 0.36,
        "counts": {
          "source1": 2
        },
        "adjustment": 0.013
      },
      "cascade_detector": {
        "repetition_ratio": 0.84,
        "price_move_pct": 0.8602589840312811,
        "max_volume_z": 0.4676437141489629,
        "tag": "HYPE_ONLY",
        "confidence_delta": 0.0
      },
      "contrarian_viewport": "POTENTIAL_CROWD_MISTAKE",
      "timescale_scores": {
        "short": {
          "divergence": 0.658,
          "price_move_pct": 0.25807769520938434,
          "volume_z": 0.4676437141489629
        },
        "mid": {
          "divergence": 0.905,
          "price_move_pct": 0.5161553904187687,
          "volume_z": 0.3741149713191703
        },
        "long": {
          "divergence": 0.741,
          "price_move_pct": 0.8602589840312811,
          "volume_z": 0.2805862284893777
        },
        "combined_divergence": 0.823,
        "aligned_horizons": 3,
        "alignment_flag": false,
        "weights": {
          "short": 0.5,
          "mid": 0.35,
          "long": 0.15
        }
      },
      "confirmation_checks": [
        {
          "name": "price_vs_narrative",
          "passed": true,
          "delta": 0.0
        },
        {
          "name": "volume_support",
          "passed": true,
          "delta": 0.0
        },
        {
          "name": "timescale_alignment",
          "passed": false,
          "delta": 0.0
        }
      ],
      "confirmation_penalty": 0.0,
      "position_sizing": {
        "confidence": 0.7864558287434407,
        "target_R": 0.46,
        "notes": [
          "linear scaling"
        ],
        "params": {
          "conf_floor": 0.65,
          "conf_cap": 0.85,
          "min_R": 0.25,
          "max_R": 1.0,
          "used_vol_norm": null
        }
      },
      "evidence_line": null,
      "thesis": {
        "action": "Buy",
        "risk_band": "Medium",
        "readiness": "Now"
      },
      "plan": {
        "1h": {
          "entries": [
            {
              "type": "trigger",
              "zone_or_trigger": 117806.67353541999
            }
          ],
          "invalidation": {
            "price": 116311.24723888,
            "condition": "close below"
          },
          "targets": [
            {
              "label": "TP1",
              "price": 118350.46491597999
            },
            {
              "label": "TP2",
              "price": 119438.04767710001
            }
          ],
          "explain": "Bias up on 1h; using trigger entries aligned with momentum (structure context). Strength elevated, timing now, action buy.",
          "source": "analysis"
        },
        "4h": {
          "entries": [
            {
              "type": "trigger",
              "zone_or_trigger": 118223.55678075
            }
          ],
          "invalidation": {
            "price": 114924.64965775001,
            "condition": "close below"
          },
          "targets": [
            {
              "label": "TP1",
              "price": 119378.17427380002
            },
            {
              "label": "TP2",
              "price": 121522.46390375002
            }
          ],
          "explain": "Bias up on 4h; using trigger entries aligned with momentum (structure context). Strength elevated, timing now, action buy.",
          "source": "analysis"
        },
        "1D": {
          "entries": [
            {
              "type": "trigger",
              "zone_or_trigger": 118718.3928492
            }
          ],
          "invalidation": {
            "price": 114099.922877,
            "condition": "close below"
          },
          "targets": [
            {
              "label": "TP1",
              "price": 120697.737123
            },
            {
              "label": "TP2",
              "price": 123996.64424600001
            }
          ],
          "explain": "Bias up on 1D; using trigger entries aligned with momentum (structure context). Strength elevated, timing now, action buy.",
          "source": "analysis"
        },
        "1W": {
          "entries": [
            {
              "type": "trigger",
              "zone_or_trigger": 119584.20922045001
            }
          ],
          "invalidation": {
            "price": 112299.61181895,
            "condition": "close below"
          },
          "targets": [
            {
              "label": "TP1",
              "price": 123226.50792119998
            },
            {
              "label": "TP2",
              "price": 129054.18584240001
            }
          ],
          "explain": "Bias up on 1W; using trigger entries aligned with momentum (structure context). Strength elevated, timing now, action buy.",
          "source": "analysis"
        }
      }
    },
    {
      "symbol": "ARB/USD",
      "symbol_type": "crypto",
      "market_hours_state": "24x7",
      "divergence": -0.796,
      "confidence": 0.882,
      "volume_z": -0.116,
      "price_move_pct": -0.49,
      "action": "HOLD",
      "summary": "Analysis for ARB/USD",
      "detail": "Basic analysis completed for ARB/USD",
      "timestamp": "2025-08-15T03:11:49.287700",
      "source_diversity": {
        "unique": 1,
        "top_source_share": 0.4,
        "counts": {
          "source1": 2
        },
        "adjustment": -0.031
      },
      "cascade_detector": {
        "repetition_ratio": 0.61,
        "price_move_pct": 0.4935002407318321,
        "max_volume_z": 0.11629656483087625,
        "tag": "",
        "confidence_delta": 0.0
      },
      "contrarian_viewport": "",
      "timescale_scores": {
        "short": {
          "divergence": -0.637,
          "price_move_pct": 0.1480500722195496,
          "volume_z": -0.11629656483087625
        },
        "mid": {
          "divergence": -0.876,
          "price_move_pct": 0.2961001444390992,
          "volume_z": -0.093037251864701
        },
        "long": {
          "divergence": -0.716,
          "price_move_pct": 0.4935002407318321,
          "volume_z": -0.06977793889852575
        },
        "combined_divergence": -0.796,
        "aligned_horizons": 2,
        "alignment_flag": false,
        "weights": {
          "short": 0.5,
          "mid": 0.35,
          "long": 0.15
        }
      },
      "confirmation_checks": [
        {
          "name": "price_vs_narrative",
          "passed": false,
          "delta": -0.02
        },
        {
          "name": "volume_support",
          "passed": false,
          "delta": 0.0
        },
        {
          "name": "timescale_alignment",
          "passed": true,
          "delta": 0.0
        }
      ],
      "confirmation_penalty": -0.02,
      "position_sizing": {
        "confidence": 0.8822243608134035,
        "target_R": 0.52,
        "notes": [
          "linear scaling"
        ],
        "params": {
          "conf_floor": 0.65,
          "conf_cap": 0.85,
          "min_R": 0.25,
          "max_R": 1.0,
          "used_vol_norm": null
        }
      },
      "evidence_line": null,
      "thesis": {
        "action": "Sell",
        "risk_band": "Medium",
        "readiness": "Now"
      },
      "plan": {
        "1h": {
          "entries": [
            {
              "type": "fade",
              "zone_or_trigger": [
                0.5065935563999999,
                0.5083137236999999
              ]
            }
          ],
          "invalidation": {
            "price": 0.5088871128,
            "condition": "close above"
          },
          "targets": [
            {
              "label": "TP1",
              "price": 0.5002862763
            },
            {
              "label": "TP2",
              "price": 0.49569916349999993
            }
          ],
          "explain": "Bias down on 1h; using fade entries into structure (structure context). Strength balanced, timing now, action sell.",
          "source": "analysis"
        },
        "4h": {
          "entries": [
            {
              "type": "fade",
              "zone_or_trigger": [
                0.5084635008,
                0.511239168
              ]
            }
          ],
          "invalidation": {
            "price": 0.514708752,
            "condition": "close above"
          },
          "targets": [
            {
              "label": "TP1",
              "price": 0.4959729984
            },
            {
              "label": "TP2",
              "price": 0.48695207999999995
            }
          ],
          "explain": "Bias down on 4h; using fade entries into structure (structure context). Strength elevated, timing now, action sell.",
          "source": "analysis"
        },
        "1D": {
          "entries": [
            {
              "type": "fade",
              "zone_or_trigger": [
                0.511239168,
                0.514708752
              ]
            }
          ],
          "invalidation": {
            "price": 0.518178336,
            "condition": "close above"
          },
          "targets": [
            {
              "label": "TP1",
              "price": 0.490421664
            },
            {
              "label": "TP2",
              "price": 0.476543328
            }
          ],
          "explain": "Bias down on 1D; using fade entries into structure (structure context). Strength elevated, timing now, action sell.",
          "source": "analysis"
        },
        "1W": {
          "entries": [
            {
              "type": "fade",
              "zone_or_trigger": [
                0.5165645759999999,
                0.522696864
              ]
            }
          ],
          "invalidation": {
            "price": 0.525763008,
            "condition": "close above"
          },
          "targets": [
            {
              "label": "TP1",
              "price": 0.47977084799999997
            },
            {
              "label": "TP2",
              "price": 0.455241696
            }
          ],
          "explain": "Bias down on 1W; using fade entries into structure (structure context). Strength elevated, timing now, action sell.",
          "source": "analysis"
        }
      }
    },
    {
      "symbol": "SOL/USD",
      "symbol_type": "crypto",
      "market_hours_state": "24x7",
      "divergence": 0.758,
      "confidence": 0.694,
      "volume_z": -0.935,
      "price_move_pct": 1.6,
      "action": "HOLD",
      "summary": "Analysis for SOL/USD",
      "detail": "Basic analysis completed for SOL/USD",
      "timestamp": "2025-08-15T03:11:49.298701",
      "source_diversity": {
        "unique": 1,
        "top_source_share": 0.43,
        "counts": {
          "source1": 3
        },
        "adjustment": -0.032
      },
      "cascade_detector": {
        "repetition_ratio": 0.51,
        "price_move_pct": 1.5975396611992538,
        "max_volume_z": 0.9354901812978913,
        "tag": "HYPE_ONLY",
        "confidence_delta": 0.0
      },
      "contrarian_viewport": "",
      "timescale_scores": {
        "short": {
          "divergence": 0.606,
          "price_move_pct": 0.4792618983597761,
          "volume_z": -0.9354901812978913
        },
        "mid": {
          "divergence": 0.833,
          "price_move_pct": 0.9585237967195522,
          "volume_z": -0.7483921450383131
        },
        "long": {
          "divergence": 0.682,
          "price_move_pct": 1.5975396611992538,
          "volume_z": -0.5612941087787348
        },
        "combined_divergence": 0.758,
        "aligned_horizons": 2,
        "alignment_flag": true,
        "weights": {
          "short": 0.5,
          "mid": 0.35,
          "long": 0.15
        }
      },
      "confirmation_checks": [
        {
          "name": "price_vs_narrative",
          "passed": true,
          "delta": 0.0
        },
        {
          "name": "volume_support",
          "passed": true,
          "delta": 0.0
        },
        {
          "name": "timescale_alignment",
          "passed": false,
          "delta": 0.0
        }
      ],
      "confirmation_penalty": 0.0,
      "position_sizing": {
        "confidence": 0.6942122772582141,
        "target_R": 0.3,
        "notes": [
          "linear scaling"
        ],
        "params": {
          "conf_floor": 0.65,
          "conf_cap": 0.85,
          "min_R": 0.25,
          "max_R": 1.0,
          "used_vol_norm": null
        }
      },
      "evidence_line": null,
      "thesis": {
        "action": "Watch",
        "risk_band": "Low",
        "readiness": "Near"
      },
      "plan": {
        "1h": {
          "entries": [
            {
              "type": "trigger",
              "zone_or_trigger": 189.00504483999998
            }
          ],
          "invalidation": {
            "price": 186.71321376,
            "condition": "close below"
          },
          "targets": [
            {
              "label": "TP1",
              "price": 189.83843796
            },
            {
              "label": "TP2",
              "price": 191.50522420000001
            }
          ],
          "explain": "Bias up on 1h; using trigger entries aligned with momentum (structure context). Strength balanced, timing near, action watch.",
          "source": "analysis"
        },
        "4h": {
          "entries": [
            {
              "type": "trigger",
              "zone_or_trigger": 189.63555269999998
            }
          ],
          "invalidation": {
            "price": 184.6133419,
            "condition": "close below"
          },
          "targets": [
            {
              "label": "TP1",
              "price": 191.39332647999998
            },
            {
              "label": "TP2",
              "price": 194.65776350000002
            }
          ],
          "explain": "Bias up on 4h; using trigger entries aligned with momentum (structure context). Strength elevated, timing near, action watch.",
          "source": "analysis"
        },
        "1D": {
          "entries": [
            {
              "type": "trigger",
              "zone_or_trigger": 190.38888432
            }
          ],
          "invalidation": {
            "price": 183.35778919999998,
            "condition": "close below"
          },
          "targets": [
            {
              "label": "TP1",
              "price": 193.40221079999998
            },
            {
              "label": "TP2",
              "price": 198.4244216
            }
          ],
          "explain": "Bias up on 1D; using trigger entries aligned with momentum (structure context). Strength elevated, timing near, action watch.",
          "source": "analysis"
        },
        "1W": {
          "entries": [
            {
              "type": "trigger",
              "zone_or_trigger": 191.7199774
            }
          ],
          "invalidation": {
            "price": 180.5867194,
            "condition": "close below"
          },
          "targets": [
            {
              "label": "TP1",
              "price": 197.28660639999998
            },
            {
              "label": "TP2",
              "price": 206.1932128
            }
          ],
          "explain": "Bias up on 1W; using trigger entries aligned with momentum (structure context). Strength elevated, timing near, action watch.",
          "source": "analysis"
        }
      }
    },
    {
      "symbol": "AAPL",
      "symbol_type": "stock",
      "market_hours_state": "CLOSED",
      "divergence": -0.7,
      "confidence": 0.641,
      "volume_z": -0.035,
      "price_move_pct": -2.5,
      "action": "HOLD",
      "summary": "Analysis for AAPL",
      "detail": "Basic analysis completed for AAPL",
      "timestamp": "2025-08-15T03:11:49.304438",
      "source_diversity": {
        "unique": 1,
        "top_source_share": 0.6,
        "counts": {
          "source1": 3
        },
        "adjustment": 0.041
      },
      "cascade_detector": {
        "repetition_ratio": 0.11,
        "price_move_pct": 2.5047289804970343,
        "max_volume_z": 0.03549856914200733,
        "tag": "HYPE_ONLY",
        "confidence_delta": 0.0
      },
      "contrarian_viewport": "",
      "timescale_scores": {
        "short": {
          "divergence": -0.56,
          "price_move_pct": 0.7514186941491102,
          "volume_z": -0.03549856914200733
        },
        "mid": {
          "divergence": -0.77,
          "price_move_pct": 1.5028373882982204,
          "volume_z": -0.028398855313605864
        },
        "long": {
          "divergence": -0.63,
          "price_move_pct": 2.5047289804970343,
          "volume_z": -0.021299141485204398
        },
        "combined_divergence": -0.7,
        "aligned_horizons": 3,
        "alignment_flag": true,
        "weights": {
          "short": 0.5,
          "mid": 0.35,
          "long": 0.15
        }
      },
      "confirmation_checks": [
        {
          "name": "price_vs_narrative",
          "passed": false,
          "delta": 0.0
        },
        {
          "name": "volume_support",
          "passed": true,
          "delta": 0.0
        },
        {
          "name": "timescale_alignment",
          "passed": true,
          "delta": 0.0
        }
      ],
      "confirmation_penalty": 0.0,
      "position_sizing": {
        "confidence": 0.641229484135704,
        "target_R": 0.0,
        "notes": [
          "below floor"
        ],
        "params": {
          "conf_floor": 0.65,
          "conf_cap": 0.85,
          "min_R": 0.25,
          "max_R": 1.0,
          "used_vol_norm": null
        }
      },
      "evidence_line": null,
      "thesis": {
        "action": "Watch",
        "risk_band": "Low",
        "readiness": "Later"
      }
    },
    {
      "symbol": "ADA/USD",
      "symbol_type": "crypto",
      "market_hours_state": "24x7",
      "divergence": -0.683,
      "confidence": 0.731,
      "volume_z": 0.056,
      "price_move_pct": 0.03,
      "action": "HOLD",
      "summary": "Analysis for ADA/USD",
      "detail": "Basic analysis completed for ADA/USD",
      "timestamp": "2025-08-15T03:11:49.286622",
      "source_diversity": {
        "unique": 3,
        "top_source_share": 0.74,
        "counts": {
          "source1": 1
        },
        "adjustment": 0.044
      },
      "cascade_detector": {
        "repetition_ratio": 0.28,
        "price_move_pct": 0.031222826908028172,
        "max_volume_z": 0.0557780866106774,
        "tag": "",
        "confidence_delta": 0.0
      },
      "contrarian_viewport": "",
      "timescale_scores": {
        "short": {
          "divergence": -0.546,
          "price_move_pct": 0.009366848072408451,
          "volume_z": 0.0557780866106774
        },
        "mid": {
          "divergence": -0.751,
          "price_move_pct": 0.018733696144816903,
          "volume_z": 0.044622469288541924
        },
        "long": {
          "divergence": -0.614,
          "price_move_pct": 0.031222826908028172,
          "volume_z": 0.03346685196640644
        },
        "combined_divergence": -0.683,
        "aligned_horizons": 2,
        "alignment_flag": true,
        "weights": {
          "short": 0.5,
          "mid": 0.35,
          "long": 0.15
        }
      },
      "confirmation_checks": [
        {
          "name": "price_vs_narrative",
          "passed": true,
          "delta": 0.0
        },
        {
          "name": "volume_support",
          "passed": false,
          "delta": -0.01
        },
        {
          "name": "timescale_alignment",
          "passed": true,
          "delta": 0.0
        }
      ],
      "confirmation_penalty": -0.01,
      "position_sizing": {
        "confidence": 0.7313516678568523,
        "target_R": 0.7,
        "notes": [
          "linear scaling"
        ],
        "params": {
          "conf_floor": 0.65,
          "conf_cap": 0.85,
          "min_R": 0.25,
          "max_R": 1.0,
          "used_vol_norm": null
        }
      },
      "evidence_line": null,
      "thesis": {
        "action": "Sell",
        "risk_band": "High",
        "readiness": "Near"
      },
      "plan": {
        "1h": {
          "entries": [
            {
              "type": "fade",
              "zone_or_trigger": [
                0.8874978192,
                0.8902711836000001
              ]
            }
          ],
          "invalidation": {
            "price": 0.8911956383999999,
            "condition": "close above"
          },
          "targets": [
            {
              "label": "TP1",
              "price": 0.8773288163999999
            },
            {
              "label": "TP2",
              "price": 0.869933178
            }
          ],
          "explain": "Bias down on 1h; using fade entries into structure (structure context). Strength balanced, timing near, action sell.",
          "source": "analysis"
        },
        "4h": {
          "entries": [
            {
              "type": "fade",
              "zone_or_trigger": [
                0.8904338028000001,
                0.8948563380000001
              ]
            }
          ],
          "invalidation": {
            "price": 0.900384507,
            "condition": "close above"
          },
          "targets": [
            {
              "label": "TP1",
              "price": 0.8705323944
            },
            {
              "label": "TP2",
              "price": 0.8561591550000001
            }
          ],
          "explain": "Bias down on 4h; using fade entries into structure (structure context). Strength elevated, timing near, action sell.",
          "source": "analysis"
        },
        "1D": {
          "entries": [
            {
              "type": "fade",
              "zone_or_trigger": [
                0.8948563380000001,
                0.900384507
              ]
            }
          ],
          "invalidation": {
            "price": 0.905912676,
            "condition": "close above"
          },
          "targets": [
            {
              "label": "TP1",
              "price": 0.861687324
            },
            {
              "label": "TP2",
              "price": 0.839574648
            }
          ],
          "explain": "Bias down on 1D; using fade entries into structure (structure context). Strength elevated, timing near, action sell.",
          "source": "analysis"
        },
        "1W": {
          "entries": [
            {
              "type": "fade",
              "zone_or_trigger": [
                0.9034910640000001,
                0.9133365960000001
              ]
            }
          ],
          "invalidation": {
            "price": 0.9182593620000001,
            "condition": "close above"
          },
          "targets": [
            {
              "label": "TP1",
              "price": 0.844417872
            },
            {
              "label": "TP2",
              "price": 0.805035744
            }
          ],
          "explain": "Bias down on 1W; using fade entries into structure (structure context). Strength balanced, timing near, action sell.",
          "source": "analysis"
        }
      }
    },
    {
      "symbol": "LTC/USD",
      "symbol_type": "crypto",
      "market_hours_state": "24x7",
      "divergence": -0.661,
      "confidence": 0.582,
      "volume_z": 0.527,
      "price_move_pct": -1.63,
      "action": "HOLD",
      "summary": "Analysis for LTC/USD",
      "detail": "Basic analysis completed for LTC/USD",
      "timestamp": "2025-08-15T03:11:49.295364",
      "source_diversity": {
        "unique": 3,
        "top_source_share": 0.47,
        "counts": {
          "source1": 3
        },
        "adjustment": 0.011
      },
      "cascade_detector": {
        "repetition_ratio": 0.33,
        "price_move_pct": 1.6270226376978063,
        "max_volume_z": 0.5267660397836809,
        "tag": "HYPE_ONLY",
        "confidence_delta": 0.0
      },
      "contrarian_viewport": "POTENTIAL_CROWD_MISTAKE",
      "timescale_scores": {
        "short": {
          "divergence": -0.529,
          "price_move_pct": 0.48810679130934187,
          "volume_z": 0.5267660397836809
        },
        "mid": {
          "divergence": -0.727,
          "price_move_pct": 0.9762135826186837,
          "volume_z": 0.4214128318269447
        },
        "long": {
          "divergence": -0.595,
          "price_move_pct": 1.6270226376978063,
          "volume_z": 0.31605962387020853
        },
        "combined_divergence": -0.661,
        "aligned_horizons": 2,
        "alignment_flag": true,
        "weights": {
          "short": 0.5,
          "mid": 0.35,
          "long": 0.15
        }
      },
      "confirmation_checks": [
        {
          "name": "price_vs_narrative",
          "passed": false,
          "delta": 0.0
        },
        {
          "name": "volume_support",
          "passed": false,
          "delta": -0.01
        },
        {
          "name": "timescale_alignment",
          "passed": true,
          "delta": 0.0
        }
      ],
      "confirmation_penalty": -0.01,
      "position_sizing": {
        "confidence": 0.5819607110633641,
        "target_R": 0.0,
        "notes": [
          "below floor"
        ],
        "params": {
          "conf_floor": 0.65,
          "conf_cap": 0.85,
          "min_R": 0.25,
          "max_R": 1.0,
          "used_vol_norm": null
        }
      },
      "evidence_line": null,
      "thesis": {
        "action": "Watch",
        "risk_band": "Low",
        "readiness": "Later"
      },
      "plan": {
        "1h": {
          "entries": [
            {
              "type": "fade",
              "zone_or_trigger": [
                120.50396116,
                120.87443203000001
              ]
            }
          ],
          "invalidation": {
            "price": 120.99792232,
            "condition": "close above"
          },
          "targets": [
            {
              "label": "TP1",
              "price": 119.14556797000002
            },
            {
              "label": "TP2",
              "price": 118.15764565
            }
          ],
          "explain": "Bias down on 1h; using fade entries into structure (structure context). Strength balanced, timing later, action watch.",
          "source": "analysis"
        },
        "4h": {
          "entries": [
            {
              "type": "fade",
              "zone_or_trigger": [
                120.89351362000002,
                121.4825227
              ]
            }
          ],
          "invalidation": {
            "price": 122.21878405000001,
            "condition": "close above"
          },
          "targets": [
            {
              "label": "TP1",
              "price": 118.24297276000001
            },
            {
              "label": "TP2",
              "price": 116.32869325
            }
          ],
          "explain": "Bias down on 4h; using fade entries into structure (structure context). Strength elevated, timing later, action watch.",
          "source": "analysis"
        },
        "1D": {
          "entries": [
            {
              "type": "fade",
              "zone_or_trigger": [
                121.4825227,
                122.21878405000001
              ]
            }
          ],
          "invalidation": {
            "price": 122.9550454,
            "condition": "close above"
          },
          "targets": [
            {
              "label": "TP1",
              "price": 117.06495460000001
            },
            {
              "label": "TP2",
              "price": 114.11990920000001
            }
          ],
          "explain": "Bias down on 1D; using fade entries into structure (structure context). Strength elevated, timing later, action watch.",
          "source": "analysis"
        },
        "1W": {
          "entries": [
            {
              "type": "fade",
              "zone_or_trigger": [
                122.638219,
                123.95232850000001
              ]
            }
          ],
          "invalidation": {
            "price": 124.60938325,
            "condition": "close above"
          },
          "targets": [
            {
              "label": "TP1",
              "price": 114.75356200000002
            },
            {
              "label": "TP2",
              "price": 109.497124
            }
          ],
          "explain": "Bias down on 1W; using fade entries into structure (structure context). Strength balanced, timing later, action watch.",
          "source": "analysis"
        }
      }
    },
    {
      "symbol": "POL/USD",
      "symbol_type": "crypto",
      "market_hours_state": "24x7",
      "divergence": 0.66,
      "confidence": 0.512,
      "volume_z": 0.55,
      "price_move_pct": 1.3,
      "action": "HOLD",
      "summary": "Analysis for POL/USD",
      "detail": "Basic analysis completed for POL/USD",
      "timestamp": "2025-08-15T03:11:49.296476",
      "source_diversity": {
        "unique": 1,
        "top_source_share": 0.65,
        "counts": {
          "source1": 3
        },
        "adjustment": -0.009
      },
      "cascade_detector": {
        "repetition_ratio": 0.22,
        "price_move_pct": 1.2964838954225595,
        "max_volume_z": 0.5504020385009829,
        "tag": "HYPE_ONLY",
        "confidence_delta": 0.0
      },
      "contrarian_viewport": "",
      "timescale_scores": {
        "short": {
          "divergence": 0.528,
          "price_move_pct": 0.3889451686267678,
          "volume_z": 0.5504020385009829
        },
        "mid": {
          "divergence": 0.726,
          "price_move_pct": 0.7778903372535356,
          "volume_z": 0.44032163080078635
        },
        "long": {
          "divergence": 0.594,
          "price_move_pct": 1.2964838954225595,
          "volume_z": 0.33024122310058973
        },
        "combined_divergence": 0.66,
        "aligned_horizons": 1,
        "alignment_flag": false,
        "weights": {
          "short": 0.5,
          "mid": 0.35,
          "long": 0.15
        }
      },
      "confirmation_checks": [
        {
          "name": "price_vs_narrative",
          "passed": false,
          "delta": 0.0
        },
        {
          "name": "volume_support",
          "passed": true,
          "delta": 0.0
        },
        {
          "name": "timescale_alignment",
          "passed": true,
          "delta": 0.0
        }
      ],
      "confirmation_penalty": 0.0,
      "position_sizing": {
        "confidence": 0.5123653061013065,
        "target_R": 0.0,
        "notes": [
          "below floor"
        ],
        "params": {
          "conf_floor": 0.65,
          "conf_cap": 0.85,
          "min_R": 0.25,
          "max_R": 1.0,
          "used_vol_norm": null
        }
      },
      "evidence_line": null,
      "thesis": {
        "action": "Watch",
        "risk_band": "Low",
        "readiness": "Later"
      },
      "plan": {
        "1h": {
          "entries": [
            {
              "type": "trigger",
              "zone_or_trigger": 0.23271548800000003
            }
          ],
          "invalidation": {
            "price": 0.230092032,
            "condition": "close below"
          },
          "targets": [
            {
              "label": "TP1",
              "price": 0.23366947200000002
            },
            {
              "label": "TP2",
              "price": 0.23557744
            }
          ],
          "explain": "Bias up on 1h; using trigger entries aligned with momentum (structure context). Strength balanced, timing later, action watch.",
          "source": "analysis"
        },
        "4h": {
          "entries": [
            {
              "type": "trigger",
              "zone_or_trigger": 0.23342216000000002
            }
          ],
          "invalidation": {
            "price": 0.22773352,
            "condition": "close below"
          },
          "targets": [
            {
              "label": "TP1",
              "price": 0.23541318400000003
            },
            {
              "label": "TP2",
              "price": 0.23911080000000004
            }
          ],
          "explain": "Bias up on 4h; using trigger entries aligned with momentum (structure context). Strength elevated, timing later, action watch.",
          "source": "analysis"
        },
        "1D": {
          "entries": [
            {
              "type": "trigger",
              "zone_or_trigger": 0.23427545600000002
            }
          ],
          "invalidation": {
            "price": 0.22631136000000002,
            "condition": "close below"
          },
          "targets": [
            {
              "label": "TP1",
              "price": 0.23768864000000003
            },
            {
              "label": "TP2",
              "price": 0.24337728
            }
          ],
          "explain": "Bias up on 1D; using trigger entries aligned with momentum (structure context). Strength elevated, timing later, action watch.",
          "source": "analysis"
        },
        "1W": {
          "entries": [
            {
              "type": "trigger",
              "zone_or_trigger": 0.23580712
            }
          ],
          "invalidation": {
            "price": 0.22311672,
            "condition": "close below"
          },
          "targets": [
            {
              "label": "TP1",
              "price": 0.24215232
            },
            {
              "label": "TP2",
              "price": 0.25230464
            }
          ],
          "explain": "Bias up on 1W; using trigger entries aligned with momentum (structure context). Strength balanced, timing later, action watch.",
          "source": "analysis"
        }
      }
    },
    {
      "symbol": "SPY",
      "symbol_type": "stock",
      "market_hours_state": "CLOSED",
      "divergence": -0.602,
      "confidence": 0.655,
      "volume_z": 0.207,
      "price_move_pct": -2.32,
      "action": "HOLD",
      "summary": "Analysis for SPY",
      "detail": "Basic analysis completed for SPY",
      "timestamp": "2025-08-15T03:11:49.303191",
      "source_diversity": {
        "unique": 1,
        "top_source_share": 0.39,
        "counts": {
          "source1": 3
        },
        "adjustment": -0.028
      },
      "cascade_detector": {
        "repetition_ratio": 0.47,
        "price_move_pct": 2.3171508352520402,
        "max_volume_z": 0.2072386551171359,
        "tag": "",
        "confidence_delta": 0.0
      },
      "contrarian_viewport": "POTENTIAL_CROWD_MISTAKE",
      "timescale_scores": {
        "short": {
          "divergence": -0.482,
          "price_move_pct": 0.695145250575612,
          "volume_z": 0.2072386551171359
        },
        "mid": {
          "divergence": -0.663,
          "price_move_pct": 1.390290501151224,
          "volume_z": 0.16579092409370874
        },
        "long": {
          "divergence": -0.542,
          "price_move_pct": 2.3171508352520402,
          "volume_z": 0.12434319307028154
        },
        "combined_divergence": -0.602,
        "aligned_horizons": 1,
        "alignment_flag": true,
        "weights": {
          "short": 0.5,
          "mid": 0.35,
          "long": 0.15
        }
      },
      "confirmation_checks": [
        {
          "name": "price_vs_narrative",
          "passed": true,
          "delta": 0.0
        },
        {
          "name": "volume_support",
          "passed": false,
          "delta": 0.0
        },
        {
          "name": "timescale_alignment",
          "passed": false,
          "delta": -0.02
        }
      ],
      "confirmation_penalty": -0.02,
      "position_sizing": {
        "confidence": 0.6550024359910958,
        "target_R": 0.51,
        "notes": [
          "linear scaling"
        ],
        "params": {
          "conf_floor": 0.65,
          "conf_cap": 0.85,
          "min_R": 0.25,
          "max_R": 1.0,
          "used_vol_norm": null
        }
      },
      "evidence_line": null,
      "thesis": {
        "action": "Watch",
        "risk_band": "Medium",
        "readiness": "Near"
      }
    },
    {
      "symbol": "OP/USD",
      "symbol_type": "crypto",
      "market_hours_state": "24x7",
      "divergence": 0.582,
      "confidence": 0.518,
      "volume_z": -0.63,
      "price_move_pct": -0.02,
      "action": "HOLD",
      "summary": "Analysis for OP/USD",
      "detail": "Basic analysis completed for OP/USD",
      "timestamp": "2025-08-15T03:11:49.297528",
      "source_diversity": {
        "unique": 2,
        "top_source_share": 0.66,
        "counts": {
          "source1": 3
        },
        "adjustment": -0.035
      },
      "cascade_detector": {
        "repetition_ratio": 0.78,
        "price_move_pct": 0.015573588519276454,
        "max_volume_z": 0.630261900306812,
        "tag": "",
        "confidence_delta": 0.0
      },
      "contrarian_viewport": "POTENTIAL_CROWD_MISTAKE",
      "timescale_scores": {
        "short": {
          "divergence": 0.466,
          "price_move_pct": 0.004672076555782936,
          "volume_z": -0.630261900306812
        },
        "mid": {
          "divergence": 0.64,
          "price_move_pct": 0.009344153111565872,
          "volume_z": -0.5042095202454496
        },
        "long": {
          "divergence": 0.524,
          "price_move_pct": 0.015573588519276454,
          "volume_z": -0.37815714018408714
        },
        "combined_divergence": 0.582,
        "aligned_horizons": 3,
        "alignment_flag": true,
        "weights": {
          "short": 0.5,
          "mid": 0.35,
          "long": 0.15
        }
      },
      "confirmation_checks": [
        {
          "name": "price_vs_narrative",
          "passed": false,
          "delta": -0.02
        },
        {
          "name": "volume_support",
          "passed": false,
          "delta": 0.0
        },
        {
          "name": "timescale_alignment",
          "passed": true,
          "delta": 0.0
        }
      ],
      "confirmation_penalty": -0.02,
      "position_sizing": {
        "confidence": 0.5177007998805472,
        "target_R": 0.0,
        "notes": [
          "below floor"
        ],
        "params": {
          "conf_floor": 0.65,
          "conf_cap": 0.85,
          "min_R": 0.25,
          "max_R": 1.0,
          "used_vol_norm": null
        }
      },
      "evidence_line": null,
      "thesis": {
        "action": "Watch",
        "risk_band": "Low",
        "readiness": "Later"
      },
      "plan": {
        "1h": {
          "entries": [
            {
              "type": "trigger",
              "zone_or_trigger": 0.744150316
            }
          ],
          "invalidation": {
            "price": 0.7362658240000001,
            "condition": "close below"
          },
          "targets": [
            {
              "label": "TP1",
              "price": 0.7470174039999999
            },
            {
              "label": "TP2",
              "price": 0.7527515799999999
            }
          ],
          "explain": "Bias up on 1h; using trigger entries aligned with momentum (structure context). Strength balanced, timing later, action watch.",
          "source": "analysis"
        },
        "4h": {
          "entries": [
            {
              "type": "trigger",
              "zone_or_trigger": 0.7462294
            }
          ],
          "invalidation": {
            "price": 0.7293118,
            "condition": "close below"
          },
          "targets": [
            {
              "label": "TP1",
              "price": 0.7521505599999999
            },
            {
              "label": "TP2",
              "price": 0.763147
            }
          ],
          "explain": "Bias up on 4h; using trigger entries aligned with momentum (structure context). Strength balanced, timing later, action watch.",
          "source": "analysis"
        },
        "1D": {
          "entries": [
            {
              "type": "trigger",
              "zone_or_trigger": 0.74876704
            }
          ],
          "invalidation": {
            "price": 0.7250824,
            "condition": "close below"
          },
          "targets": [
            {
              "label": "TP1",
              "price": 0.7589176
            },
            {
              "label": "TP2",
              "price": 0.7758352000000001
            }
          ],
          "explain": "Bias up on 1D; using trigger entries aligned with momentum (structure context). Strength balanced, timing later, action watch.",
          "source": "analysis"
        },
        "1W": {
          "entries": [
            {
              "type": "trigger",
              "zone_or_trigger": 0.75339712
            }
          ],
          "invalidation": {
            "price": 0.71540672,
            "condition": "close below"
          },
          "targets": [
            {
              "label": "TP1",
              "price": 0.77239232
            },
            {
              "label": "TP2",
              "price": 0.8027846399999999
            }
          ],
          "explain": "Bias up on 1W; using trigger entries aligned with momentum (structure context). Strength balanced, timing later, action watch.",
          "source": "analysis"
        }
      }
    },
    {
      "symbol": "UNI/USD",
      "symbol_type": "crypto",
      "market_hours_state": "24x7",
      "divergence": -0.502,
      "confidence": 0.601,
      "volume_z": -0.881,
      "price_move_pct": 0.47,
      "action": "HOLD",
      "summary": "Analysis for UNI/USD",
      "detail": "Basic analysis completed for UNI/USD",
      "timestamp": "2025-08-15T03:11:49.300896",
      "source_diversity": {
        "unique": 2,
        "top_source_share": 0.34,
        "counts": {
          "source1": 2
        },
        "adjustment": -0.034
      },
      "cascade_detector": {
        "repetition_ratio": 0.47,
        "price_move_pct": 0.4719092803215171,
        "max_volume_z": 0.8805315019347872,
        "tag": "HYPE_ONLY",
        "confidence_delta": 0.0
      },
      "contrarian_viewport": "",
      "timescale_scores": {
        "short": {
          "divergence": -0.402,
          "price_move_pct": 0.14157278409645513,
          "volume_z": -0.8805315019347872
        },
        "mid": {
          "divergence": -0.552,
          "price_move_pct": 0.28314556819291026,
          "volume_z": -0.7044252015478298
        },
        "long": {
          "divergence": -0.452,
          "price_move_pct": 0.4719092803215171,
          "volume_z": -0.5283189011608723
        },
        "combined_divergence": -0.502,
        "aligned_horizons": 3,
        "alignment_flag": true,
        "weights": {
          "short": 0.5,
          "mid": 0.35,
          "long": 0.15
        }
      },
      "confirmation_checks": [
        {
          "name": "price_vs_narrative",
          "passed": true,
          "delta": 0.0
        },
        {
          "name": "volume_support",
          "passed": true,
          "delta": -0.01
        },
        {
          "name": "timescale_alignment",
          "passed": true,
          "delta": -0.02
        }
      ],
      "confirmation_penalty": -0.03,
      "position_sizing": {
        "confidence": 0.6012257505440207,
        "target_R": 0.0,
        "notes": [
          "below floor"
        ],
        "params": {
          "conf_floor": 0.65,
          "conf_cap": 0.85,
          "min_R": 0.25,
          "max_R": 1.0,
          "used_vol_norm": null
        }
      },
      "evidence_line": null,
      "thesis": {
        "action": "Watch",
        "risk_band": "Low",
        "readiness": "Later"
      },
      "plan": {
        "1h": {
          "entries": [
            {
              "type": "fade",
              "zone_or_trigger": [
                10.787782392,
                10.816869186
              ]
            }
          ],
          "invalidation": {
            "price": 10.826564784000002,
            "condition": "close above"
          },
          "targets": [
            {
              "label": "TP1",
              "price": 10.681130814
            },
            {
              "label": "TP2",
              "price": 10.60356603
            }
          ],
          "explain": "Bias down on 1h; using fade entries into structure (structure context). Strength balanced, timing later, action watch.",
          "source": "analysis"
        },
        "4h": {
          "entries": [
            {
              "type": "fade",
              "zone_or_trigger": [
                10.816847688000001,
                10.862079480000002
              ]
            }
          ],
          "invalidation": {
            "price": 10.91861922,
            "condition": "close above"
          },
          "targets": [
            {
              "label": "TP1",
              "price": 10.613304624000001
            },
            {
              "label": "TP2",
              "price": 10.466301300000001
            }
          ],
          "explain": "Bias down on 4h; using fade entries into structure (structure context). Strength balanced, timing later, action watch.",
          "source": "analysis"
        },
        "1D": {
          "entries": [
            {
              "type": "fade",
              "zone_or_trigger": [
                10.862079480000002,
                10.91861922
              ]
            }
          ],
          "invalidation": {
            "price": 10.97515896,
            "condition": "close above"
          },
          "targets": [
            {
              "label": "TP1",
              "price": 10.522841040000001
            },
            {
              "label": "TP2",
              "price": 10.29668208
            }
          ],
          "explain": "Bias down on 1D; using fade entries into structure (structure context). Strength balanced, timing later, action watch.",
          "source": "analysis"
        },
        "1W": {
          "entries": [
            {
              "type": "fade",
              "zone_or_trigger": [
                10.95366096,
                11.05599144
              ]
            }
          ],
          "invalidation": {
            "price": 11.107156680000001,
            "condition": "close above"
          },
          "targets": [
            {
              "label": "TP1",
              "price": 10.33967808
            },
            {
              "label": "TP2",
              "price": 9.93035616
            }
          ],
          "explain": "Bias down on 1W; using fade entries into structure (structure context). Strength balanced, timing later, action watch.",
          "source": "analysis"
        }
      }
    },
    {
      "symbol": "XRP/USD",
      "symbol_type": "crypto",
      "market_hours_state": "24x7",
      "divergence": 0.462,
      "confidence": 0.752,
      "volume_z": -0.358,
      "price_move_pct": -0.33,
      "action": "HOLD",
      "summary": "Analysis for XRP/USD",
      "detail": "Basic analysis completed for XRP/USD",
      "timestamp": "2025-08-15T03:11:49.301920",
      "source_diversity": {
        "unique": 1,
        "top_source_share": 0.6,
        "counts": {
          "source1": 2
        },
        "adjustment": 0.05
      },
      "cascade_detector": {
        "repetition_ratio": 0.52,
        "price_move_pct": 0.33498898802241117,
        "max_volume_z": 0.3577864438091667,
        "tag": "",
        "confidence_delta": 0.0
      },
      "contrarian_viewport": "POTENTIAL_CROWD_MISTAKE",
      "timescale_scores": {
        "short": {
          "divergence": 0.369,
          "price_move_pct": 0.10049669640672335,
          "volume_z": -0.3577864438091667
        },
        "mid": {
          "divergence": 0.508,
          "price_move_pct": 0.2009933928134467,
          "volume_z": -0.2862291550473334
        },
        "long": {
          "divergence": 0.416,
          "price_move_pct": 0.33498898802241117,
          "volume_z": -0.2146718662855
        },
        "combined_divergence": 0.462,
        "aligned_horizons": 2,
        "alignment_flag": false,
        "weights": {
          "short": 0.5,
          "mid": 0.35,
          "long": 0.15
        }
      },
      "confirmation_checks": [
        {
          "name": "price_vs_narrative",
          "passed": true,
          "delta": -0.02
        },
        {
          "name": "volume_support",
          "passed": true,
          "delta": 0.0
        },
        {
          "name": "timescale_alignment",
          "passed": false,
          "delta": -0.02
        }
      ],
      "confirmation_penalty": -0.04,
      "position_sizing": {
        "confidence": 0.7523884825377303,
        "target_R": 0.74,
        "notes": [
          "linear scaling"
        ],
        "params": {
          "conf_floor": 0.65,
          "conf_cap": 0.85,
          "min_R": 0.25,
          "max_R": 1.0,
          "used_vol_norm": null
        }
      },
      "evidence_line": null,
      "thesis": {
        "action": "Buy",
        "risk_band": "High",
        "readiness": "Now"
      },
      "plan": {
        "1h": {
          "entries": [
            {
              "type": "trigger",
              "zone_or_trigger": 3.0460203267
            }
          ],
          "invalidation": {
            "price": 3.0169791288,
            "condition": "close below"
          },
          "targets": [
            {
              "label": "TP1",
              "price": 3.0565807623000003
            },
            {
              "label": "TP2",
              "price": 3.0777016335
            }
          ],
          "explain": "Bias up on 1h; using trigger entries aligned with momentum (structure context). Strength balanced, timing now, action buy.",
          "source": "analysis"
        },
        "4h": {
          "entries": [
            {
              "type": "trigger",
              "zone_or_trigger": 3.053412024
            }
          ],
          "invalidation": {
            "price": 2.992163928,
            "condition": "close below"
          },
          "targets": [
            {
              "label": "TP1",
              "price": 3.0748488576
            },
            {
              "label": "TP2",
              "price": 3.1146601199999995
            }
          ],
          "explain": "Bias up on 4h; using trigger entries aligned with momentum (structure context). Strength balanced, timing now, action buy.",
          "source": "analysis"
        },
        "1D": {
          "entries": [
            {
              "type": "trigger",
              "zone_or_trigger": 3.0625992384000003
            }
          ],
          "invalidation": {
            "price": 2.976851904,
            "condition": "close below"
          },
          "targets": [
            {
              "label": "TP1",
              "price": 3.099348096
            },
            {
              "label": "TP2",
              "price": 3.160596192
            }
          ],
          "explain": "Bias up on 1D; using trigger entries aligned with momentum (structure context). Strength balanced, timing now, action buy.",
          "source": "analysis"
        },
        "1W": {
          "entries": [
            {
              "type": "trigger",
              "zone_or_trigger": 3.0798434940000003
            }
          ],
          "invalidation": {
            "price": 2.940698514,
            "condition": "close below"
          },
          "targets": [
            {
              "label": "TP1",
              "price": 3.149415984
            },
            {
              "label": "TP2",
              "price": 3.260731968
            }
          ],
          "explain": "Bias up on 1W; using trigger entries aligned with momentum (structure context). Strength balanced, timing now, action buy.",
          "source": "analysis"
        }
      }
    },
    {
      "symbol": "DOGE/USD",
      "symbol_type": "crypto",
      "market_hours_state": "24x7",
      "divergence": 0.447,
      "confidence": 0.517,
      "volume_z": 0.617,
      "price_move_pct": 1.28,
      "action": "HOLD",
      "summary": "Analysis for DOGE/USD",
      "detail": "Basic analysis completed for DOGE/USD",
      "timestamp": "2025-08-15T03:11:49.292249",
      "source_diversity": {
        "unique": 1,
        "top_source_share": 0.74,
        "counts": {
          "source1": 1
        },
        "adjustment": -0.004
      },
      "cascade_detector": {
        "repetition_ratio": 0.76,
        "price_move_pct": 1.2836025571218281,
        "max_volume_z": 0.6169219515548303,
        "tag": "",
        "confidence_delta": -0.03
      },
      "contrarian_viewport": "",
      "timescale_scores": {
        "short": {
          "divergence": 0.358,
          "price_move_pct": 0.38508076713654843,
          "volume_z": 0.6169219515548303
        },
        "mid": {
          "divergence": 0.492,
          "price_move_pct": 0.7701615342730969,
          "volume_z": 0.4935375612438643
        },
        "long": {
          "divergence": 0.402,
          "price_move_pct": 1.2836025571218281,
          "volume_z": 0.3701531709328982
        },
        "combined_divergence": 0.447,
        "aligned_horizons": 3,
        "alignment_flag": true,
        "weights": {
          "short": 0.5,
          "mid": 0.35,
          "long": 0.15
        }
      },
      "confirmation_checks": [
        {
          "name": "price_vs_narrative",
          "passed": false,
          "delta": 0.0
        },
        {
          "name": "volume_support",
          "passed": false,
          "delta": 0.0
        },
        {
          "name": "timescale_alignment",
          "passed": true,
          "delta": 0.0
        }
      ],
      "confirmation_penalty": 0.0,
      "position_sizing": {
        "confidence": 0.5170356920857953,
        "target_R": 0.0,
        "notes": [
          "below floor"
        ],
        "params": {
          "conf_floor": 0.65,
          "conf_cap": 0.85,
          "min_R": 0.25,
          "max_R": 1.0,
          "used_vol_norm": null
        }
      },
      "evidence_line": null,
      "thesis": {
        "action": "Watch",
        "risk_band": "Low",
        "readiness": "Later"
      },
      "plan": {
        "1h": {
          "entries": [
            {
              "type": "trigger",
              "zone_or_trigger": 0.21934313972000002
            }
          ],
          "invalidation": {
            "price": 0.21727829408000002,
            "condition": "close below"
          },
          "targets": [
            {
              "label": "TP1",
              "price": 0.22009399268
            },
            {
              "label": "TP2",
              "price": 0.2215956986
            }
          ],
          "explain": "Bias up on 1h; using trigger entries aligned with momentum (structure context). Strength balanced, timing later, action watch.",
          "source": "analysis"
        },
        "4h": {
          "entries": [
            {
              "type": "trigger",
              "zone_or_trigger": 0.21986514880000002
            }
          ],
          "invalidation": {
            "price": 0.2155245536,
            "condition": "close below"
          },
          "targets": [
            {
              "label": "TP1",
              "price": 0.22138435711999999
            },
            {
              "label": "TP2",
              "price": 0.22420574399999998
            }
          ],
          "explain": "Bias up on 4h; using trigger entries aligned with momentum (structure context). Strength balanced, timing later, action watch.",
          "source": "analysis"
        },
        "1D": {
          "entries": [
            {
              "type": "trigger",
              "zone_or_trigger": 0.22051623807999998
            }
          ],
          "invalidation": {
            "price": 0.2144394048,
            "condition": "close below"
          },
          "targets": [
            {
              "label": "TP1",
              "price": 0.22312059520000002
            },
            {
              "label": "TP2",
              "price": 0.22746119039999999
            }
          ],
          "explain": "Bias up on 1D; using trigger entries aligned with momentum (structure context). Strength balanced, timing later, action watch.",
          "source": "analysis"
        },
        "1W": {
          "entries": [
            {
              "type": "trigger",
              "zone_or_trigger": 0.2217400934
            }
          ],
          "invalidation": {
            "price": 0.2118731154,
            "condition": "close below"
          },
          "targets": [
            {
              "label": "TP1",
              "price": 0.22667358240000002
            },
            {
              "label": "TP2",
              "price": 0.2345671648
            }
          ],
          "explain": "Bias up on 1W; using trigger entries aligned with momentum (structure context). Strength balanced, timing later, action watch.",
          "source": "analysis"
        }
      }
    },
    {
      "symbol": "LINK/USD",
      "symbol_type": "crypto",
      "market_hours_state": "24x7",
      "divergence": 0.439,
      "confidence": 0.553,
      "volume_z": -0.992,
      "price_move_pct": -0.06,
      "action": "HOLD",
      "summary": "Analysis for LINK/USD",
      "detail": "Basic analysis completed for LINK/USD",
      "timestamp": "2025-08-15T03:11:49.294304",
      "source_diversity": {
        "unique": 1,
        "top_source_share": 0.56,
        "counts": {
          "source1": 3
        },
        "adjustment": 0.031
      },
      "cascade_detector": {
        "repetition_ratio": 0.94,
        "price_move_pct": 0.06268552760320151,
        "max_volume_z": 0.9920942736039873,
        "tag": "HYPE_ONLY",
        "confidence_delta": -0.03
      },
      "contrarian_viewport": "",
      "timescale_scores": {
        "short": {
          "divergence": 0.351,
          "price_move_pct": 0.018805658280960452,
          "volume_z": -0.9920942736039873
        },
        "mid": {
          "divergence": 0.482,
          "price_move_pct": 0.037611316561920904,
          "volume_z": -0.7936754188831898
        },
        "long": {
          "divergence": 0.395,
          "price_move_pct": 0.06268552760320151,
          "volume_z": -0.5952565641623924
        },
        "combined_divergence": 0.439,
        "aligned_horizons": 2,
        "alignment_flag": false,
        "weights": {
          "short": 0.5,
          "mid": 0.35,
          "long": 0.15
        }
      },
      "confirmation_checks": [
        {
          "name": "price_vs_narrative",
          "passed": true,
          "delta": 0.0
        },
        {
          "name": "volume_support",
          "passed": false,
          "delta": -0.01
        },
        {
          "name": "timescale_alignment",
          "passed": false,
          "delta": -0.02
        }
      ],
      "confirmation_penalty": -0.03,
      "position_sizing": {
        "confidence": 0.5528858690935339,
        "target_R": 0.0,
        "notes": [
          "below floor"
        ],
        "params": {
          "conf_floor": 0.65,
          "conf_cap": 0.85,
          "min_R": 0.25,
          "max_R": 1.0,
          "used_vol_norm": null
        }
      },
      "evidence_line": null,
      "thesis": {
        "action": "Watch",
        "risk_band": "Low",
        "readiness": "Later"
      },
      "plan": {
        "1h": {
          "entries": [
            {
              "type": "trigger",
              "zone_or_trigger": 21.98598729
            }
          ],
          "invalidation": {
            "price": 21.78070056,
            "condition": "close below"
          },
          "targets": [
            {
              "label": "TP1",
              "price": 22.06063701
            },
            {
              "label": "TP2",
              "price": 22.209936449999997
            }
          ],
          "explain": "Bias up on 1h; using trigger entries aligned with momentum (structure context). Strength balanced, timing later, action watch.",
          "source": "analysis"
        },
        "4h": {
          "entries": [
            {
              "type": "trigger",
              "zone_or_trigger": 22.037676299999998
            }
          ],
          "invalidation": {
            "price": 21.6069711,
            "condition": "close below"
          },
          "targets": [
            {
              "label": "TP1",
              "price": 22.18842312
            },
            {
              "label": "TP2",
              "price": 22.4683815
            }
          ],
          "explain": "Bias up on 4h; using trigger entries aligned with momentum (structure context). Strength balanced, timing later, action watch.",
          "source": "analysis"
        },
        "1D": {
          "entries": [
            {
              "type": "trigger",
              "zone_or_trigger": 22.102282080000002
            }
          ],
          "invalidation": {
            "price": 21.4992948,
            "condition": "close below"
          },
          "targets": [
            {
              "label": "TP1",
              "price": 22.3607052
            },
            {
              "label": "TP2",
              "price": 22.7914104
            }
          ],
          "explain": "Bias up on 1D; using trigger entries aligned with momentum (structure context). Strength balanced, timing later, action watch.",
          "source": "analysis"
        },
        "1W": {
          "entries": [
            {
              "type": "trigger",
              "zone_or_trigger": 22.224410250000002
            }
          ],
          "invalidation": {
            "price": 21.243042749999997,
            "condition": "close below"
          },
          "targets": [
            {
              "label": "TP1",
              "price": 22.715094
            },
            {
              "label": "TP2",
              "price": 23.500188
            }
          ],
          "explain": "Bias up on 1W; using trigger entries aligned with momentum (structure context). Strength balanced, timing later, action watch.",
          "source": "analysis"
        }
      }
    },
    {
      "symbol": "DOT/USD",
      "symbol_type": "crypto",
      "market_hours_state": "24x7",
      "divergence": -0.438,
      "confidence": 0.549,
      "volume_z": -0.706,
      "price_move_pct": -1.11,
      "action": "HOLD",
      "summary": "Analysis for DOT/USD",
      "detail": "Basic analysis completed for DOT/USD",
      "timestamp": "2025-08-15T03:11:49.293281",
      "source_diversity": {
        "unique": 1,
        "top_source_share": 0.6,
        "counts": {
          "source1": 3
        },
        "adjustment": 0.034
      },
      "cascade_detector": {
        "repetition_ratio": 0.23,
        "price_move_pct": 1.1143813461965133,
        "max_volume_z": 0.7064235884451908,
        "tag": "HYPE_ONLY",
        "confidence_delta": 0.0
      },
      "contrarian_viewport": "POTENTIAL_CROWD_MISTAKE",
      "timescale_scores": {
        "short": {
          "divergence": -0.351,
          "price_move_pct": 0.334314403858954,
          "volume_z": -0.7064235884451908
        },
        "mid": {
          "divergence": -0.482,
          "price_move_pct": 0.668628807717908,
          "volume_z": -0.5651388707561527
        },
        "long": {
          "divergence": -0.394,
          "price_move_pct": 1.1143813461965133,
          "volume_z": -0.4238541530671145
        },
        "combined_divergence": -0.438,
        "aligned_horizons": 2,
        "alignment_flag": false,
        "weights": {
          "short": 0.5,
          "mid": 0.35,
          "long": 0.15
        }
      },
      "confirmation_checks": [
        {
          "name": "price_vs_narrative",
          "passed": true,
          "delta": 0.0
        },
        {
          "name": "volume_support",
          "passed": false,
          "delta": 0.0
        },
        {
          "name": "timescale_alignment",
          "passed": false,
          "delta": -0.02
        }
      ],
      "confirmation_penalty": -0.02,
      "position_sizing": {
        "confidence": 0.5489887785960993,
        "target_R": 0.0,
        "notes": [
          "below floor"
        ],
        "params": {
          "conf_floor": 0.65,
          "conf_cap": 0.85,
          "min_R": 0.25,
          "max_R": 1.0,
          "used_vol_norm": null
        }
      },
      "evidence_line": null,
      "thesis": {
        "action": "Watch",
        "risk_band": "Low",
        "readiness": "Later"
      },
      "plan": {
        "1h": {
          "entries": [
            {
              "type": "fade",
              "zone_or_trigger": [
                3.9373572959999996,
                3.947375268
              ]
            }
          ],
          "invalidation": {
            "price": 3.9507145919999997,
            "condition": "close above"
          },
          "targets": [
            {
              "label": "TP1",
              "price": 3.900624732
            },
            {
              "label": "TP2",
              "price": 3.87391014
            }
          ],
          "explain": "Bias down on 1h; using fade entries into structure (structure context). Strength balanced, timing later, action watch.",
          "source": "analysis"
        },
        "4h": {
          "entries": [
            {
              "type": "fade",
              "zone_or_trigger": [
                3.947120208,
                3.9625336799999995
              ]
            }
          ],
          "invalidation": {
            "price": 3.9818005199999997,
            "condition": "close above"
          },
          "targets": [
            {
              "label": "TP1",
              "price": 3.8777595839999996
            },
            {
              "label": "TP2",
              "price": 3.8276658
            }
          ],
          "explain": "Bias down on 4h; using fade entries into structure (structure context). Strength balanced, timing later, action watch.",
          "source": "analysis"
        },
        "1D": {
          "entries": [
            {
              "type": "fade",
              "zone_or_trigger": [
                3.9625336799999995,
                3.9818005199999997
              ]
            }
          ],
          "invalidation": {
            "price": 4.00106736,
            "condition": "close above"
          },
          "targets": [
            {
              "label": "TP1",
              "price": 3.84693264
            },
            {
              "label": "TP2",
              "price": 3.76986528
            }
          ],
          "explain": "Bias down on 1D; using fade entries into structure (structure context). Strength balanced, timing later, action watch.",
          "source": "analysis"
        },
        "1W": {
          "entries": [
            {
              "type": "fade",
              "zone_or_trigger": [
                3.9941611199999993,
                4.02924168
              ]
            }
          ],
          "invalidation": {
            "price": 4.04678196,
            "condition": "close above"
          },
          "targets": [
            {
              "label": "TP1",
              "price": 3.78367776
            },
            {
              "label": "TP2",
              "price": 3.6433555199999996
            }
          ],
          "explain": "Bias down on 1W; using fade entries into structure (structure context). Strength balanced, timing later, action watch.",
          "source": "analysis"
        }
      }
    },
    {
      "symbol": "ATOM/USD",
      "symbol_type": "crypto",
      "market_hours_state": "24x7",
      "divergence": -0.304,
      "confidence": 0.641,
      "volume_z": 0.904,
      "price_move_pct": -0.22,
      "action": "HOLD",
      "summary": "Analysis for ATOM/USD",
      "detail": "Basic analysis completed for ATOM/USD",
      "timestamp": "2025-08-15T03:11:49.288905",
      "source_diversity": {
        "unique": 3,
        "top_source_share": 0.73,
        "counts": {
          "source1": 1
        },
        "adjustment": 0.032
      },
      "cascade_detector": {
        "repetition_ratio": 0.54,
        "price_move_pct": 0.2238457432612769,
        "max_volume_z": 0.903847834692199,
        "tag": "",
        "confidence_delta": -0.03
      },
      "contrarian_viewport": "",
      "timescale_scores": {
        "short": {
          "divergence": -0.243,
          "price_move_pct": 0.06715372297838307,
          "volume_z": 0.903847834692199
        },
        "mid": {
          "divergence": -0.334,
          "price_move_pct": 0.13430744595676614,
          "volume_z": 0.7230782677537593
        },
        "long": {
          "divergence": -0.273,
          "price_move_pct": 0.2238457432612769,
          "volume_z": 0.5423087008153193
        },
        "combined_divergence": -0.304,
        "aligned_horizons": 3,
        "alignment_flag": false,
        "weights": {
          "short": 0.5,
          "mid": 0.35,
          "long": 0.15
        }
      },
      "confirmation_checks": [
        {
          "name": "price_vs_narrative",
          "passed": true,
          "delta": 0.0
        },
        {
          "name": "volume_support",
          "passed": true,
          "delta": 0.0
        },
        {
          "name": "timescale_alignment",
          "passed": true,
          "delta": 0.0
        }
      ],
      "confirmation_penalty": 0.0,
      "position_sizing": {
        "confidence": 0.640745499621657,
        "target_R": 0.0,
        "notes": [
          "below floor"
        ],
        "params": {
          "conf_floor": 0.65,
          "conf_cap": 0.85,
          "min_R": 0.25,
          "max_R": 1.0,
          "used_vol_norm": null
        }
      },
      "evidence_line": null,
      "thesis": {
        "action": "Watch",
        "risk_band": "Low",
        "readiness": "Later"
      },
      "plan": {
        "1h": {
          "entries": [
            {
              "type": "fade",
              "zone_or_trigger": [
                4.4632254,
                4.47314445
              ]
            }
          ],
          "invalidation": {
            "price": 4.4764508,
            "condition": "close above"
          },
          "targets": [
            {
              "label": "TP1",
              "price": 4.42685555
            },
            {
              "label": "TP2",
              "price": 4.400404750000001
            }
          ],
          "explain": "Bias down on 1h; using fade entries into structure (structure context). Strength muted, timing later, action watch.",
          "source": "analysis"
        },
        "4h": {
          "entries": [
            {
              "type": "fade",
              "zone_or_trigger": [
                4.4722678,
                4.487113
              ]
            }
          ],
          "invalidation": {
            "price": 4.505669500000001,
            "condition": "close above"
          },
          "targets": [
            {
              "label": "TP1",
              "price": 4.4054644000000005
            },
            {
              "label": "TP2",
              "price": 4.3572175
            }
          ],
          "explain": "Bias down on 4h; using fade entries into structure (structure context). Strength muted, timing later, action watch.",
          "source": "analysis"
        },
        "1D": {
          "entries": [
            {
              "type": "fade",
              "zone_or_trigger": [
                4.487113,
                4.505669500000001
              ]
            }
          ],
          "invalidation": {
            "price": 4.5242260000000005,
            "condition": "close above"
          },
          "targets": [
            {
              "label": "TP1",
              "price": 4.375774
            },
            {
              "label": "TP2",
              "price": 4.3015479999999995
            }
          ],
          "explain": "Bias down on 1D; using fade entries into structure (structure context). Strength muted, timing later, action watch.",
          "source": "analysis"
        },
        "1W": {
          "entries": [
            {
              "type": "fade",
              "zone_or_trigger": [
                4.518797,
                4.5531955
              ]
            }
          ],
          "invalidation": {
            "price": 4.57039475,
            "condition": "close above"
          },
          "targets": [
            {
              "label": "TP1",
              "price": 4.312406
            },
            {
              "label": "TP2",
              "price": 4.174812
            }
          ],
          "explain": "Bias down on 1W; using fade entries into structure (structure context). Strength muted, timing later, action watch.",
          "source": "analysis"
        }
      }
    },
    {
      "symbol": "MSFT",
      "symbol_type": "stock",
      "market_hours_state": "CLOSED",
      "divergence": -0.184,
      "confidence": 0.534,
      "volume_z": 0.128,
      "price_move_pct": -1.76,
      "action": "HOLD",
      "summary": "Analysis for MSFT",
      "detail": "Basic analysis completed for MSFT",
      "timestamp": "2025-08-15T03:11:49.305654",
      "source_diversity": {
        "unique": 1,
        "top_source_share": 0.61,
        "counts": {
          "source1": 1
        },
        "adjustment": -0.025
      },
      "cascade_detector": {
        "repetition_ratio": 0.74,
        "price_move_pct": 1.7601363532072332,
        "max_volume_z": 0.12751650074489196,
        "tag": "HYPE_ONLY",
        "confidence_delta": 0.0
      },
      "contrarian_viewport": "",
      "timescale_scores": {
        "short": {
          "divergence": -0.147,
          "price_move_pct": 0.5280409059621699,
          "volume_z": 0.12751650074489196
        },
        "mid": {
          "divergence": -0.202,
          "price_move_pct": 1.0560818119243398,
          "volume_z": 0.10201320059591357
        },
        "long": {
          "divergence": -0.165,
          "price_move_pct": 1.7601363532072332,
          "volume_z": 0.07650990044693518
        },
        "combined_divergence": -0.184,
        "aligned_horizons": 3,
        "alignment_flag": false,
        "weights": {
          "short": 0.5,
          "mid": 0.35,
          "long": 0.15
        }
      },
      "confirmation_checks": [
        {
          "name": "price_vs_narrative",
          "passed": true,
          "delta": 0.0
        },
        {
          "name": "volume_support",
          "passed": false,
          "delta": -0.01
        },
        {
          "name": "timescale_alignment",
          "passed": true,
          "delta": -0.02
        }
      ],
      "confirmation_penalty": -0.03,
      "position_sizing": {
        "confidence": 0.5338485750543234,
        "target_R": 0.0,
        "notes": [
          "below floor"
        ],
        "params": {
          "conf_floor": 0.65,
          "conf_cap": 0.85,
          "min_R": 0.25,
          "max_R": 1.0,
          "used_vol_norm": null
        }
      },
      "evidence_line": null,
      "thesis": {
        "action": "Watch",
        "risk_band": "Low",
        "readiness": "Later"
      }
    },
    {
      "symbol": "TRX/USD",
      "symbol_type": "crypto",
      "market_hours_state": "24x7",
      "divergence": -0.144,
      "confidence": 0.615,
      "volume_z": 0.202,
      "price_move_pct": 0.53,
      "action": "HOLD",
      "summary": "Analysis for TRX/USD",
      "detail": "Basic analysis completed for TRX/USD",
      "timestamp": "2025-08-15T03:11:49.299833",
      "source_diversity": {
        "unique": 1,
        "top_source_share": 0.39,
        "counts": {
          "source1": 2
        },
        "adjustment": 0.044
      },
      "cascade_detector": {
        "repetition_ratio": 0.02,
        "price_move_pct": 0.5265100671140958,
        "max_volume_z": 0.2017349974042819,
        "tag": "",
        "confidence_delta": 0.0
      },
      "contrarian_viewport": "",
      "timescale_scores": {
        "short": {
          "divergence": -0.115,
          "price_move_pct": 0.1579530201342287,
          "volume_z": 0.2017349974042819
        },
        "mid": {
          "divergence": -0.158,
          "price_move_pct": 0.3159060402684574,
          "volume_z": 0.16138799792342554
        },
        "long": {
          "divergence": -0.129,
          "price_move_pct": 0.5265100671140958,
          "volume_z": 0.12104099844256914
        },
        "combined_divergence": -0.144,
        "aligned_horizons": 3,
        "alignment_flag": false,
        "weights": {
          "short": 0.5,
          "mid": 0.35,
          "long": 0.15
        }
      },
      "confirmation_checks": [
        {
          "name": "price_vs_narrative",
          "passed": false,
          "delta": 0.0
        },
        {
          "name": "volume_support",
          "passed": true,
          "delta": 0.0
        },
        {
          "name": "timescale_alignment",
          "passed": false,
          "delta": 0.0
        }
      ],
      "confirmation_penalty": 0.0,
      "position_sizing": {
        "confidence": 0.6147957752870624,
        "target_R": 0.0,
        "notes": [
          "below floor"
        ],
        "params": {
          "conf_floor": 0.65,
          "conf_cap": 0.85,
          "min_R": 0.25,
          "max_R": 1.0,
          "used_vol_norm": null
        }
      },
      "evidence_line": null,
      "thesis": {
        "action": "Watch",
        "risk_band": "Low",
        "readiness": "Later"
      },
      "plan": {
        "1h": {
          "entries": [
            {
              "type": "fade",
              "zone_or_trigger": [
                0.35467034799999997,
                0.355323109
              ]
            }
          ],
          "invalidation": {
            "price": 0.355540696,
            "condition": "close above"
          },
          "targets": [
            {
              "label": "TP1",
              "price": 0.352276891
            },
            {
              "label": "TP2",
              "price": 0.350536195
            }
          ],
          "explain": "Bias down on 1h; using fade entries into structure (structure context). Strength muted, timing later, action watch.",
          "source": "analysis"
        },
        "4h": {
          "entries": [
            {
              "type": "fade",
              "zone_or_trigger": [
                0.3551968024,
                0.356128004
              ]
            }
          ],
          "invalidation": {
            "price": 0.357292006,
            "condition": "close above"
          },
          "targets": [
            {
              "label": "TP1",
              "price": 0.3510063952
            },
            {
              "label": "TP2",
              "price": 0.34797999
            }
          ],
          "explain": "Bias down on 4h; using fade entries into structure (structure context). Strength muted, timing later, action watch.",
          "source": "analysis"
        },
        "1D": {
          "entries": [
            {
              "type": "fade",
              "zone_or_trigger": [
                0.356128004,
                0.357292006
              ]
            }
          ],
          "invalidation": {
            "price": 0.35845600800000005,
            "condition": "close above"
          },
          "targets": [
            {
              "label": "TP1",
              "price": 0.349143992
            },
            {
              "label": "TP2",
              "price": 0.344487984
            }
          ],
          "explain": "Bias down on 1D; using fade entries into structure (structure context). Strength muted, timing later, action watch.",
          "source": "analysis"
        },
        "1W": {
          "entries": [
            {
              "type": "fade",
              "zone_or_trigger": [
                0.35825080400000003,
                0.36047620599999997
              ]
            }
          ],
          "invalidation": {
            "price": 0.36158890699999996,
            "condition": "close above"
          },
          "targets": [
            {
              "label": "TP1",
              "price": 0.344898392
            },
            {
              "label": "TP2",
              "price": 0.335996784
            }
          ],
          "explain": "Bias down on 1W; using fade entries into structure (structure context). Strength muted, timing later, action watch.",
          "source": "analysis"
        }
      }
    },
    {
      "symbol": "ETH/USD",
      "symbol_type": "crypto",
      "market_hours_state": "24x7",
      "divergence": 0.02,
      "confidence": 0.671,
      "volume_z": 0.424,
      "price_move_pct": 0.57,
      "action": "HOLD",
      "summary": "Analysis for ETH/USD",
      "detail": "Basic analysis completed for ETH/USD",
      "timestamp": "2025-08-15T03:11:49.285567",
      "source_diversity": {
        "unique": 2,
        "top_source_share": 0.39,
        "counts": {
          "source1": 1
        },
        "adjustment": 0.025
      },
      "cascade_detector": {
        "repetition_ratio": 0.72,
        "price_move_pct": 0.5670830414687877,
        "max_volume_z": 0.42428226599327057,
        "tag": "",
        "confidence_delta": -0.03
      },
      "contrarian_viewport": "",
      "timescale_scores": {
        "short": {
          "divergence": 0.016,
          "price_move_pct": 0.17012491244063632,
          "volume_z": 0.42428226599327057
        },
        "mid": {
          "divergence": 0.022,
          "price_move_pct": 0.34024982488127264,
          "volume_z": 0.3394258127946165
        },
        "long": {
          "divergence": 0.018,
          "price_move_pct": 0.5670830414687877,
          "volume_z": 0.25456935959596233
        },
        "combined_divergence": 0.02,
        "aligned_horizons": 2,
        "alignment_flag": false,
        "weights": {
          "short": 0.5,
          "mid": 0.35,
          "long": 0.15
        }
      },
      "confirmation_checks": [
        {
          "name": "price_vs_narrative",
          "passed": true,
          "delta": -0.02
        },
        {
          "name": "volume_support",
          "passed": true,
          "delta": 0.0
        },
        {
          "name": "timescale_alignment",
          "passed": true,
          "delta": 0.0
        }
      ],
      "confirmation_penalty": -0.02,
      "position_sizing": {
        "confidence": 0.6713509880411379,
        "target_R": 0.41,
        "notes": [
          "linear scaling"
        ],
        "params": {
          "conf_floor": 0.65,
          "conf_cap": 0.85,
          "min_R": 0.25,
          "max_R": 1.0,
          "used_vol_norm": null
        }
      },
      "evidence_line": null,
      "thesis": {
        "action": "Watch",
        "risk_band": "Medium",
        "readiness": "Near"
      },
      "plan": {
        "1h": {
          "entries": [
            {
              "type": "trigger",
              "zone_or_trigger": 4473.3139872
            }
          ],
          "invalidation": {
            "price": 4447.9627008,
            "condition": "close below"
          },
          "targets": [
            {
              "label": "TP1",
              "price": 4482.5326368
            },
            {
              "label": "TP2",
              "price": 4500.969936
            }
          ],
          "explain": "Bias up on 1h; using trigger entries aligned with momentum (structure context). Strength muted, timing near, action watch.",
          "source": "analysis"
        },
        "4h": {
          "entries": [
            {
              "type": "trigger",
              "zone_or_trigger": 4478.057304
            }
          ],
          "invalidation": {
            "price": 4431.428088,
            "condition": "close below"
          },
          "targets": [
            {
              "label": "TP1",
              "price": 4494.377529599999
            },
            {
              "label": "TP2",
              "price": 4524.686519999999
            }
          ],
          "explain": "Bias up on 4h; using trigger entries aligned with momentum (structure context). Strength muted, timing near, action watch.",
          "source": "analysis"
        },
        "1D": {
          "entries": [
            {
              "type": "trigger",
              "zone_or_trigger": 4485.051686399999
            }
          ],
          "invalidation": {
            "price": 4419.770783999999,
            "condition": "close below"
          },
          "targets": [
            {
              "label": "TP1",
              "price": 4513.029216
            },
            {
              "label": "TP2",
              "price": 4559.658431999999
            }
          ],
          "explain": "Bias up on 1D; using trigger entries aligned with momentum (structure context). Strength muted, timing near, action watch.",
          "source": "analysis"
        },
        "1W": {
          "entries": [
            {
              "type": "trigger",
              "zone_or_trigger": 4501.1039279999995
            }
          ],
          "invalidation": {
            "price": 4385.424168,
            "condition": "close below"
          },
          "targets": [
            {
              "label": "TP1",
              "price": 4558.943808
            },
            {
              "label": "TP2",
              "price": 4651.487615999999
            }
          ],
          "explain": "Bias up on 1W; using trigger entries aligned with momentum (structure context). Strength muted, timing near, action watch.",
          "source": "analysis"
        }
      }
    }
  ],
  "polymarket": [
    {
      "market_name": "Ethereum hits $5,000 by August 31, 2025",
      "stance": "Engage",
      "readiness": "Near",
      "edge_label": "market cheap",
      "rationale": "Market pricing looks favorable versus our view. Timing is approaching; monitor for clean triggers.",
      "implied_prob": 0.64,
      "implied_pct": 64.0,
      "tb_internal_prob": 0.6693333333333333,
      "liquidity_usd": null,
      "event_end_date": "2025-08-31T23:59:59+00:00",
      "market_id": null,
      "quality_score": null
    },
    {
      "market_name": "Ethereum hits $4,800 by August 31, 2025",
      "stance": "Engage",
      "readiness": "Near",
      "edge_label": "market cheap",
      "rationale": "Market pricing looks favorable versus our view. Timing is approaching; monitor for clean triggers.",
      "implied_prob": 0.9,
      "implied_pct": 90.0,
      "tb_internal_prob": 0.9293333333333333,
      "liquidity_usd": null,
      "event_end_date": "2025-08-31T23:59:59+00:00",
      "market_id": null,
      "quality_score": null
    },
    {
      "market_name": "Ethereum hits new all-time high by August 31, 2025",
      "stance": "Engage",
      "readiness": "Near",
      "edge_label": "market cheap",
      "rationale": "Market pricing looks favorable versus our view. Timing is approaching; monitor for clean triggers.",
      "implied_prob": 0.87,
      "implied_pct": 87.0,
      "tb_internal_prob": 0.8993333333333333,
      "liquidity_usd": null,
      "event_end_date": "2025-08-31T23:59:59+00:00",
      "market_id": null,
      "quality_score": null
    }
  ]
}